pycore/__init__.py
pycore/data/__init__.py
pycore/data/database/__init__.py
pycore/data/database/mysql_connection.py
pycore/data/entity/__init__.py
pycore/data/entity/config.py
pycore/data/entity/globalvar.py
pycore/utils/__init__.py
pycore/utils/aes_utils.py
pycore/utils/batch_queue.py
pycore/utils/http_utils.py
pycore/utils/logger_utils.py
pycore/utils/rc4_utils.py
pycore/utils/redis_utils.py
pycore/utils/rsa_utils.py
pycore/utils/stringutils.py
pycore/utils/tcp_count.py
pycore/utils/time_utils.py
pycore_utils-0.0.33.dist-info/METADATA
pycore_utils-0.0.33.dist-info/WHEEL
pycore_utils-0.0.33.dist-info/top_level.txt
pycore_utils-0.0.33.dist-info/RECORD
